allegro5/__init__.py
allegro5/allegro.py
allegro5/demo/__init__.py
allegro5/demo/pong.py
allegro5-1.0.6.data/data/lib/site-packages/allegro5/demo/fixed_font.tga
allegro5-1.0.6.dist-info/METADATA
allegro5-1.0.6.dist-info/WHEEL
allegro5-1.0.6.dist-info/top_level.txt
allegro5-1.0.6.dist-info/RECORD
