Metadata-Version: 2.1
Name: allegro5
Version: 1.0.6
Summary: Allegro 5 game development library (originaly in C) wrapped in Python
Home-page: https://github.com/liballeg/allegro5/
Author: Amin Guermazi
Author-email: mino260806@gmail.com
License: UNKNOWN
Platform: UNKNOWN
Classifier: Programming Language :: Python :: 3
Classifier: License :: OSI Approved :: zlib/libpng License
Classifier: Operating System :: OS Independent
Requires-Python: >=3.6
